{
  "diagnosis": [
    {
      "id": 1,
      "name": "Congenital Heart Disease"
    },
    {
      "id": 2,
      "name": "Congestive Heart Failure"
    },
    {
      "id": 3,
      "name": "Acute Rheumatic Fever"
    },
    {
      "id": 4,
      "name": "Anemia"
    },
    {
      "id": 5,
      "name": "Arrhythmia"
    },
    {
      "id": 6,
      "name": "Autism Spectrum Disorder"
    },
    {
      "id": 7,
      "name": "Cerebral Palsy"
    },
    {
      "id": 8,
      "name": "Epilepsy"
    },
    {
      "id": 9,
      "name": "Febrile Seizure"
    },
    {
      "id": 10,
      "name": "Hydrocephalus"
    },
    {
      "id": 11,
      "name": "ITP"
    },
    {
      "id": 12,
      "name": "Meningitis"
    },
    {
      "id": 13,
      "name": "Muscular Dystrophy"
    },
    {
      "id": 14,
      "name": "Spartan Hypertention"
    },
    {
      "id": 15,
      "name": "Chicken pox"
    },
    {
      "id": 16,
      "name": "Dengue"
    },
    {
      "id": 17,
      "name": "Diphtheria"
    },
    {
      "id": 18,
      "name": "Enteric fever"
    },
    {
      "id": 19,
      "name": "Hepatitis"
    },
    {
      "id": 20,
      "name": "Influenze"
    },
    {
      "id": 21,
      "name": "Malaria"
    },
    {
      "id": 22,
      "name": "Measles"
    },
    {
      "id": 23,
      "name": "Mumps"
    },
    {
      "id": 24,
      "name": "Necrotizing Enterocolitis"
    },
    {
      "id": 25,
      "name": "Neonatal Sepsis "
    },
    {
      "id": 26,
      "name": "Perinatal Asphyxia"
    },
    {
      "id": 27,
      "name": "Respiratory Distress Syndrome"
    },
    {
      "id": 28,
      "name": "Transient Tachypnea of new born"
    },
    {
      "id": 29,
      "name": "Acute Gastroenteritis - AGE"
    },
    {
      "id": 30,
      "name": "Constipation"
    },
    {
      "id": 31,
      "name": "Gastritis"
    },
    {
      "id": 32,
      "name": "Hyperactive Airway Disease"
    },
    {
      "id": 33,
      "name": "Pneumonia"
    },
    {
      "id": 34,
      "name": "Pulmonary TB"
    },
    {
      "id": 35,
      "name": "Upper Respiratory Tract Infection"
    },
    {
      "id": 36,
      "name": "ARMD"
    },
    {
      "id": 37,
      "name": "Blunt Trauma"
    },
    {
      "id": 38,
      "name": "Cataract"
    },
    {
      "id": 39,
      "name": "Congenital Nasal Obstruction"
    },
    {
      "id": 40,
      "name": "Corneal Foreign body"
    },
    {
      "id": 41,
      "name": "Corneal Ulcer"
    },
    {
      "id": 42,
      "name": "CRVO"
    },
    {
      "id": 43,
      "name": "CSR"
    },
    {
      "id": 44,
      "name": "Diabetic Retinopathy"
    },
    {
      "id": 45,
      "name": "Dry eye"
    },
    {
      "id": 47,
      "name": "Isotretinoin"
    },
    {
      "id": 46,
      "name": "Glaucoma"
    },
    {
      "id": 47,
      "name": "Hypertensive Retinopathy"
    },
    {
      "id": 48,
      "name": "Orbital Cellulitis"
    },
    {
      "id": 49,
      "name": "Preseptal Cellulitis"
    },
    {
      "id": 50,
      "name": " Refractive error "
    },
    {
      "id": 51,
      "name": "Retinal detachment"
    },
    {
      "id": 52,
      "name": "Thyroid eye disease"
    },
    {
      "id": 53,
      "name": "Uveitis"
    },
    {
      "id": 54,
      "name": "Bells palsy"
    },
    {
      "id": 55,
      "name": "Blepharitis"
    },
    {
      "id": 56,
      "name": "Chalazion"
    },
    {
      "id": 57,
      "name": " Conjuctivitis"
    },
    {
      "id": 58,
      "name": "Episcleritis / Scleritis"
    },
    {
      "id": 59,
      "name": "Nerve palsy"
    },
    {
      "id": 60,
      "name": "Optic Neuritis"
    },
    {
      "id": 61,
      "name": "Pinguecula"
    },
    {
      "id": 62,
      "name": "Pterygium"
    },
    {
      "id": 63,
      "name": "Ptosis"
    },
    {
      "id": 64,
      "name": "Squint"
    },
    {
      "id": 65,
      "name": "Staphyloma"
    },
    {
      "id": 66,
      "name": "STYE - hordeolum internum"
    },
    {
      "id": 67,
      "name": "VKS- spring catarrh"
    },
    {
      "id": 68,
      "name": "Abortion"
    },
    {
      "id": 69,
      "name": "ANC - pregnancy"
    },
    {
      "id": 70,
      "name": "Anemia of pregnancy"
    },
    {
      "id": 71,
      "name": " APH"
    },
    {
      "id": 72,
      "name": "AVB"
    },
    {
      "id": 73,
      "name": " Ectopic pregnancy"
    },
    {
      "id": 74,
      "name": "Endometriosis"
    },
    {
      "id": 75,
      "name": "GDM"
    },
    {
      "id": 76,
      "name": "Hyperemesis gravidarum"
    },
    {
      "id": 77,
      "name": "Infertility"
    },
    {
      "id": 78,
      "name": "Obstetric cholestasis"
    },
    {
      "id": 79,
      "name": "PID"
    },
    {
      "id": 80,
      "name": "PLOS"
    },
    {
      "id": 81,
      "name": "Preeclampsia / Eclampsia "
    },
    {
      "id": 82,
      "name": "Prolapse"
    },
    {
      "id": 84,
      "name": "Acne"
    },
    {
      "id": 85,
      "name": "AGA - Androgenetic alopecia "
    },
    {
      "id": 86,
      "name": "Balanoposthitis"
    },
    {
      "id": 87,
      "name": "Hansen's Disease"
    },
    {
      "id": 88,
      "name": "Herpes zoster"
    },
    {
      "id": 89,
      "name": "Immunobullous disease"
    },
    {
      "id": 90,
      "name": "Melasma"
    },
    {
      "id": 91,
      "name": "Pityriasis versicolor"
    },
    {
      "id": 92,
      "name": "Psoriasis"
    },
    {
      "id": 93,
      "name": "Scabies"
    },
    {
      "id": 94,
      "name": "Tinea"
    },
    {
      "id": 95,
      "name": "Urticaria"
    },
    {
      "id": 96,
      "name": "Varicella"
    },
    {
      "id": 97,
      "name": "Vitiligo"
    },
    {
      "id": 98,
      "name": "VVC"
    },
    {
      "id": 99,
      "name": "Warts disease"
    },
    {
      "id": 100,
      "name": "Asthma "
    },
    {
      "id": 101,
      "name": "Ca lung"
    },
    {
      "id": 102,
      "name": "COPD"
    },
    {
      "id": 103,
      "name": "COVID - 19"
    },
    {
      "id": 104,
      "name": "LRTI"
    },
    {
      "id": 105,
      "name": "Pleural effusion"
    },
    {
      "id": 106,
      "name": "Pneumonia"
    },
    {
      "id": 107,
      "name": "Pneumothorax"
    },
    {
      "id": 108,
      "name": "Tuberculosis"
    },
    {
      "id": 109,
      "name": "URTI- upper respiratory infection"
    },
    {
      "id": 110,
      "name": "Allergic rhinitis"
    },
    {
      "id": 111,
      "name": "ASOM"
    },
    {
      "id": 112,
      "name": "BPPV"
    },
    {
      "id": 113,
      "name": "CSOM"
    },
    {
      "id": 114,
      "name": "Deviated nasal septum"
    },
    {
      "id": 115,
      "name": "Ear wax"
    },
    {
      "id": 116,
      "name": "Epistaxis"
    },
    {
      "id": 117,
      "name": "ETD"
    },
    {
      "id": 118,
      "name": "F.B. Ear"
    },
    {
      "id": 119,
      "name": "F.B. Nose"
    },
    {
      "id": 120,
      "name": "LPRD"
    },
    {
      "id": 121,
      "name": "Nasal polyposis"
    },
    {
      "id": 122,
      "name": "OME"
    },
    {
      "id": 123,
      "name": "Otitis externa"
    },
    {
      "id": 124,
      "name": "Otomycosis"
    },
    {
      "id": 125,
      "name": "Pharyngitis"
    },
    {
      "id": 126,
      "name": "Presbycusis"
    },
    {
      "id": 127,
      "name": "Rhinosinusitis"
    },
    {
      "id": 128,
      "name": "Tonsillitis"
    },
    {
      "id": 129,
      "name": "Vocal cord nodule"
    },
    {
      "id": 130,
      "name": "Vocal cord polyp"
    },
    {
      "id": 131,
      "name": "IHD/CAD"
    },
    {
      "id": 132,
      "name": "ACS"
    },
    {
      "id": 133,
      "name": "ADHF"
    },
    {
      "id": 134,
      "name": "HFrEF"
    },
    {
      "id": 135,
      "name": "HFpEF"
    },
    {
      "id": 136,
      "name": "RHD"
    },
    {
      "id": 137,
      "name": "Valvular heart disease "
    },
    {
      "id": 138,
      "name": "Acute kidney injury "
    },
    {
      "id": 139,
      "name": "Chronic kidney injury"
    },
    {
      "id": 140,
      "name": "Nephrotic syndrome"
    },
    {
      "id": 141,
      "name": "Nephritic syndrome"
    },
    {
      "id": 142,
      "name": "Polycystic kidney disease"
    },
    {
      "id": 143,
      "name": "Cushings"
    },
    {
      "id": 144,
      "name": "Diabetes - type 1"
    },
    {
      "id": 145,
      "name": "Diabetes - type 2"
    },
    {
      "id": 146,
      "name": "hyperthyroidism"
    },
    {
      "id": 147,
      "name": "hypothyroidism"
    },
    {
      "id": 148,
      "name": "Metabolic syndrome"
    },
    {
      "id": 149,
      "name": "Rheumatoid arthritis"
    },
    {
      "id": 150,
      "name": "Osteoarthritis"
    },
    {
      "id": 151,
      "name": "Ankylosing spondylitis"
    },
    {
      "id": 152,
      "name": "Psoriatic arthritis"
    },
    {
      "id": 153,
      "name": "Gout"
    },
    {
      "id": 154,
      "name": "Sjogren's syndrome"
    },
    {
      "id": 156,
      "name": "Infection arthritis"
    },
    {
      "id": 157,
      "name": "Cervical spondylosis"
    },
    {
      "id": 158,
      "name": "Pott's spene"
    },
    {
      "id": 159,
      "name": "COPD"
    },
    {
      "id": 160,
      "name": "LRTI"
    },
    {
      "id": 161,
      "name": "Asthma"
    },
    {
      "id": 162,
      "name": "Tuberculosis"
    },
    {
      "id": 163,
      "name": "Pleural effusion"
    },
    {
      "id": 164,
      "name": "Acid peptic disease"
    },
    {
      "id": 165,
      "name": "Acute gastritis"
    },
    {
      "id": 166,
      "name": "Acute gastroenteritis"
    },
    {
      "id": 167,
      "name": "Acute hepatitis"
    },
    {
      "id": 168,
      "name": " Cholecystitis"
    },
    {
      "id": 169,
      "name": "Inflammatory bowel disease"
    },
    {
      "id": 170,
      "name": "Irritable bowel syndrome"
    },
    {
      "id": 171,
      "name": "NASH"
    },
    {
      "id": 172,
      "name": "Pancreatitis"
    },
    {
      "id": 173,
      "name": "UTI"
    },
    {
      "id": 174,
      "name": "Typhoid"
    },
    {
      "id": 175,
      "name": "Malaria"
    },
    {
      "id": 176,
      "name": "Dengue"
    },
    {
      "id": 177,
      "name": "COVID "
    },
    {
      "id": 179,
      "name": "Acute spinal cord injury"
    },
    {
      "id": 180,
      "name": "Alzheimer's disease"
    },
    {
      "id": 181,
      "name": "Amyotrophic lateral sclerosis"
    },
    {
      "id": 182,
      "name": "Bell's palsy"
    },
    {
      "id": 183,
      "name": "Cerebral aneurysm"
    },
    {
      "id": 184,
      "name": "CVA infarct"
    },
    {
      "id": 185,
      "name": "Epilepsy and seizure"
    },
    {
      "id": 186,
      "name": "Hydrocephalus"
    },
    {
      "id": 187,
      "name": "Meningitis"
    },
    {
      "id": 188,
      "name": "Migraine"
    },
    {
      "id": 189,
      "name": "Parkinson's disease"
    },
    {
      "id": 190,
      "name": "Stroke"
    }
  ]
}
